testinggenie/__init__.py
testinggenie/client.py
testinggenie/main.py
testinggenie/utils.py
testinggenie-0.4.0.dist-info/METADATA
testinggenie-0.4.0.dist-info/WHEEL
testinggenie-0.4.0.dist-info/top_level.txt
testinggenie-0.4.0.dist-info/RECORD
