Metadata-Version: 2.1
Name: testinggenie
Version: 0.4.0
Summary: A package to generate unit test cases from code snippets using the Anthropic API.
Author: Meesala Sai Dhanush
Author-email: saidhanushm1@gmail.com
Classifier: Programming Language :: Python :: 3
Classifier: License :: OSI Approved :: MIT License
Classifier: Operating System :: OS Independent
Requires-Python: >=3.6
Requires-Dist: tqdm
Requires-Dist: anthropic
